CLI.py
colors.py
cli_essentials-0.0.4.dist-info/LICENSE
cli_essentials-0.0.4.dist-info/METADATA
cli_essentials-0.0.4.dist-info/WHEEL
cli_essentials-0.0.4.dist-info/top_level.txt
cli_essentials-0.0.4.dist-info/RECORD
