Metadata-Version: 2.1
Name: cli-essentials
Version: 0.0.4
Summary: Python CLI building essentials
Home-page: https://github.com/DanGill/cli-essentials
Author: Daniel Gill
License: MIT
Keywords: cli-essentials cli essentials simple color colour easy basic
Platform: UNKNOWN
Classifier: Programming Language :: Python :: 3
Classifier: License :: OSI Approved :: MIT License
Requires-Python: ~=3.3
License-File: LICENSE
